b2l/__init__.py
b2l/base.py
b2l/core.py
b2l/models.py
b2l/time/AR_model.py
b2l/time/AUTO_SARIMAX_model.py
b2l/time/CATBOOST_model.py
b2l/time/HWES_model.py
b2l/time/LIGHTGBM_model.py
b2l/time/LSTM_model.py
b2l/time/MA_model.py
b2l/time/PROPHET_model.py
b2l/time/SARIMAX_model.py
b2l/time/XGBOOST_model.py
b2l/time/YTY_model.py
b2l/time/__init__.py
b2l-0.8.dist-info/LICENSE
b2l-0.8.dist-info/METADATA
b2l-0.8.dist-info/WHEEL
b2l-0.8.dist-info/top_level.txt
b2l-0.8.dist-info/RECORD
