Metadata-Version: 2.1
Name: b2l
Version: 0.8
Summary: Brain2Logic package to deal with API and Maching Learning
Home-page: UNKNOWN
Author: Pisarev Andrei
Author-email: pisarev@brain2logic.com
License: UNKNOWN
Platform: UNKNOWN
Classifier: Programming Language :: Python :: 3
Classifier: License :: OSI Approved :: MIT License
Classifier: Operating System :: OS Independent
